aquaview/__init__.py
aquaview/client.py
aquaview-0.2.0.dist-info/METADATA
aquaview-0.2.0.dist-info/WHEEL
aquaview-0.2.0.dist-info/top_level.txt
aquaview-0.2.0.dist-info/RECORD
