Metadata-Version: 2.4
Name: aquaview
Version: 0.2.0
Summary: Python SDK for accessing oceanographic datasets through the AQUAVIEW API
Author: AQUAVIEW Team
License-Expression: MIT
Project-URL: Homepage, https://aquaview.org
Project-URL: Documentation, https://service.aquaview.org/schema/swagger
Requires-Python: >=3.8
Requires-Dist: requests>=2.25.0
